neos3files.py
neos3files-1.0.0.dist-info/LICENSE
neos3files-1.0.0.dist-info/METADATA
neos3files-1.0.0.dist-info/WHEEL
neos3files-1.0.0.dist-info/top_level.txt
neos3files-1.0.0.dist-info/RECORD
