Metadata-Version: 2.1
Name: neos3files
Version: 1.0.0
Summary: High-level async Python library for working with S3-compatible storage
Author-email: Neosart Team <ruslan@ruisvip.ru>
Maintainer-email: Ruslan Isaev <ruslan@ruisvip.ru>
License: MIT
Project-URL: Homepage, https://github.com/NeosartDevs/NeoS3Files
Project-URL: Documentation, https://github.com/NeosartDevs/NeoS3Files#readme
Project-URL: Repository, https://github.com/NeosartDevs/NeoS3Files.git
Project-URL: Bug Tracker, https://github.com/NeosartDevs/NeoS3Files/issues
Keywords: s3,aws,storage,async,minio,object-storage,cloud-storage
Classifier: Development Status :: 4 - Beta
Classifier: Intended Audience :: Developers
Classifier: License :: OSI Approved :: MIT License
Classifier: Operating System :: OS Independent
Classifier: Programming Language :: Python :: 3
Classifier: Programming Language :: Python :: 3.7
Classifier: Programming Language :: Python :: 3.8
Classifier: Programming Language :: Python :: 3.9
Classifier: Programming Language :: Python :: 3.10
Classifier: Programming Language :: Python :: 3.11
Classifier: Programming Language :: Python :: 3.12
Classifier: Framework :: AsyncIO
Requires-Python: >=3.7
License-File: LICENSE
Requires-Dist: aioboto3 >=11.0.0
Requires-Dist: aiofiles >=23.0.0
Requires-Dist: botocore >=1.29.0
Provides-Extra: dev
Requires-Dist: black >=23.0.0 ; extra == 'dev'
Requires-Dist: flake8 >=6.0.0 ; extra == 'dev'
Requires-Dist: mypy >=1.0.0 ; extra == 'dev'
Requires-Dist: pytest-asyncio >=0.21.0 ; extra == 'dev'
Requires-Dist: pytest >=7.0.0 ; extra == 'dev'
Provides-Extra: test
Requires-Dist: pytest-asyncio >=0.21.0 ; extra == 'test'
Requires-Dist: pytest-cov >=4.0.0 ; extra == 'test'
Requires-Dist: pytest >=7.0.0 ; extra == 'test'
